mcp_config_sync/__init__.py
mcp_config_sync/apps.py
mcp_config_sync/cli.py
mcp_config_sync/py.typed
mcp_config_sync/sync.py
mcp_config_sync-0.2.0.dist-info/licenses/LICENSE
mcp_config_sync-0.2.0.dist-info/METADATA
mcp_config_sync-0.2.0.dist-info/WHEEL
mcp_config_sync-0.2.0.dist-info/entry_points.txt
mcp_config_sync-0.2.0.dist-info/top_level.txt
mcp_config_sync-0.2.0.dist-info/RECORD
