Metadata-Version: 2.4
Name: mcp-config-sync
Version: 0.2.0
Summary: Synchronize Model Context Protocol (MCP) server configurations across different tools and applications
Author-email: Jon <jon@zer0day.net>
Maintainer-email: Jon <jon@zer0day.net>
License-Expression: MIT
Project-URL: Homepage, https://github.com/jon-the-dev/mcp_config_sync
Project-URL: Repository, https://github.com/jon-the-dev/mcp_config_sync
Project-URL: Issues, https://github.com/jon-the-dev/mcp_config_sync/issues
Project-URL: Documentation, https://github.com/jon-the-dev/mcp_config_sync#readme
Keywords: mcp,model-context-protocol,configuration,sync,ai,tools
Classifier: Development Status :: 4 - Beta
Classifier: Intended Audience :: Developers
Classifier: Operating System :: OS Independent
Classifier: Programming Language :: Python :: 3
Classifier: Programming Language :: Python :: 3.12
Classifier: Programming Language :: Python :: 3.13
Classifier: Topic :: Software Development :: Libraries :: Python Modules
Classifier: Topic :: System :: Systems Administration
Classifier: Topic :: Utilities
Requires-Python: >=3.12
License-File: LICENSE
Requires-Dist: python-dotenv>=1.0.0
Provides-Extra: dev
Requires-Dist: pytest>=7.0.0; extra == "dev"
Requires-Dist: pytest-cov>=4.0.0; extra == "dev"
Requires-Dist: black>=23.0.0; extra == "dev"
Requires-Dist: isort>=5.12.0; extra == "dev"
Requires-Dist: flake8>=6.0.0; extra == "dev"
Requires-Dist: mypy>=1.0.0; extra == "dev"
Dynamic: license-file
